lanku/__init__.py
lanku/__main__.py
lanku/__version__.py
lanku/config.py
lanku/home.py
lanku/node.py
lanku/peer.py
lanku/systray.py
lanku/ui.py
lanku/assets/btn_bell-hover.png
lanku/assets/btn_bell-push.png
lanku/assets/btn_bell.png
lanku/assets/btn_close-hover.png
lanku/assets/btn_close-push.png
lanku/assets/btn_close.png
lanku/assets/btn_connect-hover.png
lanku/assets/btn_connect-push.png
lanku/assets/btn_connect.png
lanku/assets/btn_disconnect-hover.png
lanku/assets/btn_disconnect-push.png
lanku/assets/btn_disconnect.png
lanku/assets/btn_link-hover.png
lanku/assets/btn_link-push.png
lanku/assets/btn_link.png
lanku/assets/btn_peer-hover.png
lanku/assets/btn_peer-push.png
lanku/assets/btn_peer.png
lanku/assets/btn_txfr-hover.png
lanku/assets/btn_txfr-push.png
lanku/assets/btn_txfr.png
lanku/assets/graphics.svg
lanku/assets/tab_config-active.png
lanku/assets/tab_config-hover.png
lanku/assets/tab_config.png
lanku/assets/tab_labels-active.png
lanku/assets/tab_labels-hover.png
lanku/assets/tab_labels.png
lanku/assets/tab_nodes-active.png
lanku/assets/tab_nodes-hover.png
lanku/assets/tab_nodes.png
lanku/assets/tab_peers-active.png
lanku/assets/tab_peers-hover.png
lanku/assets/tab_peers.png
lanku/peers/__init__.py
lanku/peers/link.py
lanku-0.1.6.data/data/share/applications/com.lannocc.lanku.desktop
lanku-0.1.6.dist-info/LICENSE
lanku-0.1.6.dist-info/METADATA
lanku-0.1.6.dist-info/WHEEL
lanku-0.1.6.dist-info/entry_points.txt
lanku-0.1.6.dist-info/top_level.txt
lanku-0.1.6.dist-info/RECORD
