Metadata-Version: 2.1
Name: lanku
Version: 0.1.6
Summary: LANK User
Home-page: https://github.com/lannocc/lanku
Author: LANNOCC (Shawn A. Wilson)
Author-email: lannocc@yahoo.com
Classifier: Programming Language :: Python :: 3
Classifier: License :: OSI Approved :: MIT License
Classifier: Operating System :: OS Independent
License-File: LICENSE
Requires-Dist: appdirs
Requires-Dist: lank (>=0.4.5)
Requires-Dist: pyglet
Requires-Dist: pystray
Requires-Dist: requests
